fluidattacks_batch_client/__init__.py
fluidattacks_batch_client/_cli.py
fluidattacks_batch_client/_logger.py
fluidattacks_batch_client/_utils.py
fluidattacks_batch_client/core.py
fluidattacks_batch_client/decode.py
fluidattacks_batch_client/py.typed
fluidattacks_batch_client/api/__init__.py
fluidattacks_batch_client/api/_core.py
fluidattacks_batch_client/api/_client_1/__init__.py
fluidattacks_batch_client/api/_client_1/_get_command.py
fluidattacks_batch_client/api/_client_1/_list_jobs.py
fluidattacks_batch_client/api/_client_1/_send_job.py
fluidattacks_batch_client/sender/__init__.py
fluidattacks_batch_client/sender/_core.py
fluidattacks_batch_client/sender/_send.py
fluidattacks_batch_client-0.1.0.dist-info/entry_points.txt
fluidattacks_batch_client-0.1.0.dist-info/WHEEL
fluidattacks_batch_client-0.1.0.dist-info/METADATA
fluidattacks_batch_client-0.1.0.dist-info/RECORD
