Metadata-Version: 2.4
Name: fluidattacks_batch_client
Version: 0.1.0
Summary: AWS batch python client
Author-email: Engineering Team <development@fluidattacks.com>
Requires-Python: >=3.11
Requires-Dist: click >=8.1.8, <9.0.0
Requires-Dist: boto3 >=1.42.32, <2.0.0
Requires-Dist: fa_purity >=2.5.0, <3.0.0
